run_all_the_tests/__init__.py
run_all_the_tests/py.typed
run_all_the_tests/test_case.py
run_all_the_tests/test_runner.py
run_all_the_tests-0.1.21.dist-info/WHEEL
run_all_the_tests-0.1.21.dist-info/METADATA
run_all_the_tests-0.1.21.dist-info/RECORD
