Metadata-Version: 2.1
Name: run-all-the-tests
Version: 0.1.21
Summary: Make sure both 'python -m pytest' and 'pytest' run your tests.
Home-page: https://github.com/gkedge/run-all-the-tests
License: MIT
Keywords: testing,import,sys.path,packaging,dependency,pyproject.toml
Author: Greg Kedge
Author-email: gregwork@kedges.com
Requires-Python: >=3.6,<4.0
Classifier: Intended Audience :: Developers
Classifier: License :: OSI Approved :: MIT License
Classifier: Natural Language :: English
Classifier: Operating System :: OS Independent
Classifier: Programming Language :: Python :: 3
Classifier: Programming Language :: Python :: 3.6
Classifier: Programming Language :: Python :: 3.7
Classifier: Programming Language :: Python :: 3.8
Classifier: Programming Language :: Python :: 3.9
Classifier: Topic :: Software Development :: Libraries
Classifier: Topic :: Software Development :: Testing
Classifier: Topic :: Utilities
Project-URL: Bug Tracker, https://github.com/gkedge/run-all-the-tests/issues
Project-URL: Repository, https://github.com/gkedge/run-all-the-tests
